{
  "indexes": [
    {
      "collectionGroup": "rooms",
      "queryScope": "COLLECTION_GROUP",
      "fields": [
        { "fieldPath": "roomId", "order": "ASCENDING" },
        { "fieldPath": "userId", "order": "ASCENDING" }
      ]
    },
    {
      "collectionGroup": "versions",
      "queryScope": "COLLECTION",
      "fields": [
        { "fieldPath": "timeStamp", "order": "ASCENDING" }
      ]
    },
    {
      "collectionGroup": "versions",
      "queryScope": "COLLECTION",
      "fields": [
        { "fieldPath": "timeStamp", "order": "DESCENDING" }
      ]
    },
    {
      "collectionGroup": "documents",
      "queryScope": "COLLECTION",
      "fields": [
        { "fieldPath": "replayShareId", "order": "ASCENDING" }
      ]
    }
  ],
  "fieldOverrides": []
}
